better_exchook/__init__.py
better_exchook/better_exchook.py
better_exchook/demo.py
better_exchook/test.py
better_exchook-1.20260120.84725.dist-info/licenses/License.txt
better_exchook-1.20260120.84725.dist-info/METADATA
better_exchook-1.20260120.84725.dist-info/WHEEL
better_exchook-1.20260120.84725.dist-info/top_level.txt
better_exchook-1.20260120.84725.dist-info/RECORD
